azizitc/__init__.py
azizitc-0.1.0.dist-info/METADATA
azizitc-0.1.0.dist-info/WHEEL
azizitc-0.1.0.dist-info/top_level.txt
azizitc-0.1.0.dist-info/RECORD
